[
  {
    "id": "1.21.11",
    "name": "1.21.11",
    "release_target": null,
    "type": "release",
    "stable": true,
    "data_version": 4671,
    "protocol_version": 774,
    "data_pack_version": 94,
    "data_pack_version_minor": 1,
    "resource_pack_version": 75,
    "resource_pack_version_minor": 0,
    "build_time": "2025-12-09T12:20:42+00:00",
    "release_time": "2025-12-09T12:23:30+00:00",
    "sha1": "3f42d3ea921915b36c581a435ed03683a7023fb1"
  },
  {
    "id": "1.21.10",
    "name": "1.21.10",
    "release_target": null,
    "type": "release",
    "stable": true,
    "data_version": 4556,
    "protocol_version": 773,
    "data_pack_version": 88,
    "data_pack_version_minor": 0,
    "resource_pack_version": 69,
    "resource_pack_version_minor": 0,
    "build_time": "2025-10-07T09:14:11+00:00",
    "release_time": "2025-10-07T09:17:23+00:00",
    "sha1": "b8ac7ed26100bd79830df1de207fbeefe7fab62f"
  },
  {
    "id": "1.21.9",
    "name": "1.21.9",
    "release_target": null,
    "type": "release",
    "stable": true,
    "data_version": 4554,
    "protocol_version": 773,
    "data_pack_version": 88,
    "data_pack_version_minor": 0,
    "resource_pack_version": 69,
    "resource_pack_version_minor": 0,
    "build_time": "2025-09-30T11:55:33+00:00",
    "release_time": "2025-09-30T11:58:43+00:00",
    "sha1": "5f1f5deb7ee3d6c5999c0beb8c28048126f632cb"
  },
  {
    "id": "1.21.8",
    "name": "1.21.8",
    "release_target": null,
    "type": "release",
    "stable": true,
    "data_version": 4440,
    "protocol_version": 772,
    "data_pack_version": 81,
    "data_pack_version_minor": 0,
    "resource_pack_version": 64,
    "resource_pack_version_minor": 0,
    "build_time": "2025-07-17T12:00:57+00:00",
    "release_time": "2025-07-17T12:04:02+00:00",
    "sha1": "de42c11e1e1aadaa60e03790ffc85c5f361e6e03"
  },
  {
    "id": "1.21.7",
    "name": "1.21.7",
    "release_target": null,
    "type": "release",
    "stable": true,
    "data_version": 4438,
    "protocol_version": 772,
    "data_pack_version": 81,
    "data_pack_version_minor": 0,
    "resource_pack_version": 64,
    "resource_pack_version_minor": 0,
    "build_time": "2025-06-30T09:29:28+00:00",
    "release_time": "2025-06-30T09:32:16+00:00",
    "sha1": "f6f0ba30a39264f195be62d537f91d77f20808c9"
  },
  {
    "id": "1.21.6",
    "name": "1.21.6",
    "release_target": null,
    "type": "release",
    "stable": true,
    "data_version": 4435,
    "protocol_version": 771,
    "data_pack_version": 80,
    "data_pack_version_minor": 0,
    "resource_pack_version": 63,
    "resource_pack_version_minor": 0,
    "build_time": "2025-06-17T11:07:28+00:00",
    "release_time": "2025-06-17T11:10:28+00:00",
    "sha1": "5a77629a75690b414a6ad465b8184601073db809"
  },
  {
    "id": "1.21.5",
    "name": "1.21.5",
    "release_target": null,
    "type": "release",
    "stable": true,
    "data_version": 4325,
    "protocol_version": 770,
    "data_pack_version": 71,
    "data_pack_version_minor": 0,
    "resource_pack_version": 55,
    "resource_pack_version_minor": 0,
    "build_time": "2025-03-25T12:11:48+00:00",
    "release_time": "2025-03-25T12:14:58+00:00",
    "sha1": "96c2641b5f5f63caf031d8eae4df623236904fef"
  },
  {
    "id": "1.21.4",
    "name": "1.21.4",
    "release_target": null,
    "type": "release",
    "stable": true,
    "data_version": 4189,
    "protocol_version": 769,
    "data_pack_version": 61,
    "data_pack_version_minor": 0,
    "resource_pack_version": 46,
    "resource_pack_version_minor": 0,
    "build_time": "2024-12-03T10:09:48+00:00",
    "release_time": "2024-12-03T10:12:57+00:00",
    "sha1": "f89b85ca7eed4fe47d2566a1d4714a61c84271dc"
  },
  {
    "id": "1.21.3",
    "name": "1.21.3",
    "release_target": null,
    "type": "release",
    "stable": true,
    "data_version": 4082,
    "protocol_version": 768,
    "data_pack_version": 57,
    "data_pack_version_minor": 0,
    "resource_pack_version": 42,
    "resource_pack_version_minor": 0,
    "build_time": "2024-10-23T12:25:27+00:00",
    "release_time": "2024-10-23T12:28:15+00:00",
    "sha1": "f98d807ec8babd00598d20c0d74d083fed5fb1d4"
  },
  {
    "id": "1.21.2",
    "name": "1.21.2",
    "release_target": null,
    "type": "release",
    "stable": true,
    "data_version": 4080,
    "protocol_version": 768,
    "data_pack_version": 57,
    "data_pack_version_minor": 0,
    "resource_pack_version": 42,
    "resource_pack_version_minor": 0,
    "build_time": "2024-10-22T09:55:49+00:00",
    "release_time": "2024-10-22T09:58:55+00:00",
    "sha1": "bf5e8fc794ee056c4da103b82c66cf25faa53148"
  },
  {
    "id": "1.21.1",
    "name": "1.21.1",
    "release_target": null,
    "type": "release",
    "stable": true,
    "data_version": 3955,
    "protocol_version": 767,
    "data_pack_version": 48,
    "data_pack_version_minor": 0,
    "resource_pack_version": 34,
    "resource_pack_version_minor": 0,
    "build_time": "2024-08-08T12:21:55+00:00",
    "release_time": "2024-08-08T12:24:45+00:00",
    "sha1": "a56257b4bc475ecac33571b51b68b33ac046fc72"
  },
  {
    "id": "1.21",
    "name": "1.21",
    "release_target": null,
    "type": "release",
    "stable": true,
    "data_version": 3953,
    "protocol_version": 767,
    "data_pack_version": 48,
    "data_pack_version_minor": 0,
    "resource_pack_version": 34,
    "resource_pack_version_minor": 0,
    "build_time": "2024-06-13T08:21:21+00:00",
    "release_time": "2024-06-13T08:24:03+00:00",
    "sha1": "b73d817c3d86fd8b9673327f86a4a84dd7f8a4cc"
  },
  {
    "id": "1.20.6",
    "name": "1.20.6",
    "release_target": null,
    "type": "release",
    "stable": true,
    "data_version": 3839,
    "protocol_version": 766,
    "data_pack_version": 41,
    "data_pack_version_minor": 0,
    "resource_pack_version": 32,
    "resource_pack_version_minor": 0,
    "build_time": "2024-04-29T12:38:06+00:00",
    "release_time": "2024-04-29T12:40:45+00:00",
    "sha1": "1ff24d754b1703e99015a3dd6a58019b5c7888f1"
  },
  {
    "id": "1.20.5",
    "name": "1.20.5",
    "release_target": null,
    "type": "release",
    "stable": true,
    "data_version": 3837,
    "protocol_version": 766,
    "data_pack_version": 41,
    "data_pack_version_minor": 0,
    "resource_pack_version": 32,
    "resource_pack_version_minor": 0,
    "build_time": "2024-04-23T11:51:33+00:00",
    "release_time": "2024-04-23T11:54:12+00:00",
    "sha1": "616afcd51c4ec636d0bbe88df97abb0304332e75"
  },
  {
    "id": "1.20.4",
    "name": "1.20.4",
    "release_target": null,
    "type": "release",
    "stable": true,
    "data_version": 3700,
    "protocol_version": 765,
    "data_pack_version": 26,
    "data_pack_version_minor": 0,
    "resource_pack_version": 22,
    "resource_pack_version_minor": 0,
    "build_time": "2023-12-07T12:53:30+00:00",
    "release_time": "2023-12-07T12:56:20+00:00",
    "sha1": "44ce5d5ee61147b42b8962a97583dc31495a7502"
  },
  {
    "id": "1.20.3",
    "name": "1.20.3",
    "release_target": null,
    "type": "release",
    "stable": true,
    "data_version": 3698,
    "protocol_version": 765,
    "data_pack_version": 26,
    "data_pack_version_minor": 0,
    "resource_pack_version": 22,
    "resource_pack_version_minor": 0,
    "build_time": "2023-12-04T12:04:50+00:00",
    "release_time": "2023-12-04T12:10:32+00:00",
    "sha1": "6e893ce6256ba994f78998234b39614b0f956fe9"
  },
  {
    "id": "1.20.2",
    "name": "1.20.2",
    "release_target": null,
    "type": "release",
    "stable": true,
    "data_version": 3578,
    "protocol_version": 764,
    "data_pack_version": 18,
    "data_pack_version_minor": 0,
    "resource_pack_version": 18,
    "resource_pack_version_minor": 0,
    "build_time": "2023-09-20T09:00:26+00:00",
    "release_time": "2023-09-20T09:02:57+00:00",
    "sha1": "78b2e897f502e0fc113319a4f41c107a9e38f21a"
  },
  {
    "id": "1.20.1",
    "name": "1.20.1",
    "release_target": null,
    "type": "release",
    "stable": true,
    "data_version": 3465,
    "protocol_version": 763,
    "data_pack_version": 15,
    "data_pack_version_minor": 0,
    "resource_pack_version": 15,
    "resource_pack_version_minor": 0,
    "build_time": "2023-06-12T13:23:26+00:00",
    "release_time": "2023-06-12T13:25:51+00:00",
    "sha1": "9318a951bbc903b54a21463a7eb8c4d451f7b132"
  },
  {
    "id": "1.20",
    "name": "1.20",
    "release_target": null,
    "type": "release",
    "stable": true,
    "data_version": 3463,
    "protocol_version": 763,
    "data_pack_version": 15,
    "data_pack_version_minor": 0,
    "resource_pack_version": 15,
    "resource_pack_version_minor": 0,
    "build_time": "2023-06-02T08:33:51+00:00",
    "release_time": "2023-06-02T08:36:17+00:00",
    "sha1": "98e72fe61c3c2017a61056507c76fcf3b9c43642"
  },
  {
    "id": "1.19.4",
    "name": "1.19.4",
    "release_target": null,
    "type": "release",
    "stable": true,
    "data_version": 3337,
    "protocol_version": 762,
    "data_pack_version": 12,
    "data_pack_version_minor": 0,
    "resource_pack_version": 13,
    "resource_pack_version_minor": 0,
    "build_time": "2023-03-14T12:53:56+00:00",
    "release_time": "2023-03-14T12:56:18+00:00",
    "sha1": "41d8ff1adecb90a9cc7bd49cb9054016554ebce8"
  },
  {
    "id": "1.19.3",
    "name": "1.19.3",
    "release_target": null,
    "type": "release",
    "stable": true,
    "data_version": 3218,
    "protocol_version": 761,
    "data_pack_version": 10,
    "data_pack_version_minor": 0,
    "resource_pack_version": 12,
    "resource_pack_version_minor": 0,
    "build_time": "2022-12-07T08:14:04+00:00",
    "release_time": "2022-12-07T08:17:18+00:00",
    "sha1": "f13274fdbcc1e7270e7a4cb8983726f37de06369"
  },
  {
    "id": "1.19.2",
    "name": "1.19.2",
    "release_target": "1.19.2",
    "type": "release",
    "stable": true,
    "data_version": 3120,
    "protocol_version": 760,
    "data_pack_version": 10,
    "data_pack_version_minor": 0,
    "resource_pack_version": 9,
    "resource_pack_version_minor": 0,
    "build_time": "2022-08-05T11:55:20+00:00",
    "release_time": "2022-08-05T11:57:05+00:00",
    "sha1": "ed548106acf3ac7e8205a6ee8fd2710facfa164f"
  },
  {
    "id": "1.19.1",
    "name": "1.19.1",
    "release_target": "1.19.1",
    "type": "release",
    "stable": true,
    "data_version": 3117,
    "protocol_version": 760,
    "data_pack_version": 10,
    "data_pack_version_minor": 0,
    "resource_pack_version": 9,
    "resource_pack_version_minor": 0,
    "build_time": "2022-07-27T09:23:42+00:00",
    "release_time": "2022-07-27T09:25:33+00:00",
    "sha1": "39d5e8925d37490c6f2abb2e02b8c6f1b35719df"
  },
  {
    "id": "1.19",
    "name": "1.19",
    "release_target": "1.19",
    "type": "release",
    "stable": true,
    "data_version": 3105,
    "protocol_version": 759,
    "data_pack_version": 10,
    "data_pack_version_minor": 0,
    "resource_pack_version": 9,
    "resource_pack_version_minor": 0,
    "build_time": "2022-06-07T09:40:26+00:00",
    "release_time": "2022-06-07T09:42:18+00:00",
    "sha1": "14bbfb25fb1c1c798e3c9b9482b081a78d1f3a9d"
  },
  {
    "id": "1.18.2",
    "name": "1.18.2",
    "release_target": "1.18.2",
    "type": "release",
    "stable": true,
    "data_version": 2975,
    "protocol_version": 758,
    "data_pack_version": 9,
    "data_pack_version_minor": 0,
    "resource_pack_version": 8,
    "resource_pack_version_minor": 0,
    "build_time": "2022-02-28T10:40:37+00:00",
    "release_time": "2022-02-28T10:42:45+00:00",
    "sha1": "334b33fcba3c9be4b7514624c965256535bd7eba"
  },
  {
    "id": "1.18.1",
    "name": "1.18.1",
    "release_target": "1.18.1",
    "type": "release",
    "stable": true,
    "data_version": 2865,
    "protocol_version": 757,
    "data_pack_version": 8,
    "data_pack_version_minor": 0,
    "resource_pack_version": 8,
    "resource_pack_version_minor": 0,
    "build_time": "2021-12-10T08:21:01+00:00",
    "release_time": "2021-12-10T08:23:00+00:00",
    "sha1": "7ff864e988a2c29907154d5f9701e87e5d5e554a"
  },
  {
    "id": "1.18",
    "name": "1.18",
    "release_target": "1.18",
    "type": "release",
    "stable": true,
    "data_version": 2860,
    "protocol_version": 757,
    "data_pack_version": 8,
    "data_pack_version_minor": 0,
    "resource_pack_version": 8,
    "resource_pack_version_minor": 0,
    "build_time": "2021-11-30T09:14:30+00:00",
    "release_time": "2021-11-30T09:16:29+00:00",
    "sha1": "7367ea8b7cad7c7830192441bb2846be0d2ceeac"
  },
  {
    "id": "1.17.1",
    "name": "1.17.1",
    "release_target": "1.17.1",
    "type": "release",
    "stable": true,
    "data_version": 2730,
    "protocol_version": 756,
    "data_pack_version": 7,
    "data_pack_version_minor": 0,
    "resource_pack_version": 7,
    "resource_pack_version_minor": 0,
    "build_time": "2021-07-06T11:59:45+00:00",
    "release_time": "2021-07-06T12:01:34+00:00",
    "sha1": "e0e7ab5ed6f55bbd874ef95be3c9356d67e64b57"
  },
  {
    "id": "1.17",
    "name": "1.17",
    "release_target": "1.17",
    "type": "release",
    "stable": true,
    "data_version": 2724,
    "protocol_version": 755,
    "data_pack_version": 7,
    "data_pack_version_minor": 0,
    "resource_pack_version": 7,
    "resource_pack_version_minor": 0,
    "build_time": "2021-06-08T10:58:54+00:00",
    "release_time": "2021-06-08T11:00:40+00:00",
    "sha1": "0d9ace8a2ecfd1f4c782786f4b985a499240ff12"
  },
  {
    "id": "1.16.5",
    "name": "1.16.5",
    "release_target": "1.16.5",
    "type": "release",
    "stable": true,
    "data_version": 2586,
    "protocol_version": 754,
    "data_pack_version": 6,
    "data_pack_version_minor": 0,
    "resource_pack_version": 6,
    "resource_pack_version_minor": 0,
    "build_time": "2021-01-14T16:03:41+00:00",
    "release_time": "2021-01-14T16:05:32+00:00",
    "sha1": "fba9f7833e858a1257d810d21a3a9e3c967f9077"
  },
  {
    "id": "1.16.4",
    "name": "1.16.4",
    "release_target": "1.16.4",
    "type": "release",
    "stable": true,
    "data_version": 2584,
    "protocol_version": 754,
    "data_pack_version": 6,
    "data_pack_version_minor": 0,
    "resource_pack_version": 6,
    "resource_pack_version_minor": 0,
    "build_time": "2020-10-29T15:47:51+00:00",
    "release_time": "2020-10-29T15:49:37+00:00",
    "sha1": "596ad61fda7612d9edf8881cf81869276bdb7f82"
  },
  {
    "id": "1.16.3",
    "name": "1.16.3",
    "release_target": "1.16.3",
    "type": "release",
    "stable": true,
    "data_version": 2580,
    "protocol_version": 753,
    "data_pack_version": 6,
    "data_pack_version_minor": 0,
    "resource_pack_version": 6,
    "resource_pack_version_minor": 0,
    "build_time": "2020-09-10T13:40:50+00:00",
    "release_time": "2020-09-10T13:42:37+00:00",
    "sha1": "6485dd131ef68c968041a9f6fd73094b027e42e1"
  },
  {
    "id": "1.16.2",
    "name": "1.16.2",
    "release_target": "1.16.2",
    "type": "release",
    "stable": true,
    "data_version": 2578,
    "protocol_version": 751,
    "data_pack_version": 6,
    "data_pack_version_minor": 0,
    "resource_pack_version": 6,
    "resource_pack_version_minor": 0,
    "build_time": "2020-08-11T10:11:57+00:00",
    "release_time": "2020-08-11T10:13:46+00:00",
    "sha1": "998d9ef5770d05c20d760dc16cf85151f35009f2"
  },
  {
    "id": "1.16.1",
    "name": "1.16.1",
    "release_target": "1.16.1",
    "type": "release",
    "stable": true,
    "data_version": 2567,
    "protocol_version": 736,
    "data_pack_version": 5,
    "data_pack_version_minor": 0,
    "resource_pack_version": 5,
    "resource_pack_version_minor": 0,
    "build_time": "2020-06-24T10:29:54+00:00",
    "release_time": "2020-06-24T10:31:40+00:00",
    "sha1": "54fa3af57d041d2771e66d390197b2c0288e697c"
  },
  {
    "id": "1.16",
    "name": "1.16",
    "release_target": "1.16",
    "type": "release",
    "stable": true,
    "data_version": 2566,
    "protocol_version": 735,
    "data_pack_version": 5,
    "data_pack_version_minor": 0,
    "resource_pack_version": 5,
    "resource_pack_version_minor": 0,
    "build_time": "2020-06-23T16:19:09+00:00",
    "release_time": "2020-06-23T16:20:52+00:00",
    "sha1": "e9d21d375f9c961f0e9731d4e463306d76e77c48"
  },
  {
    "id": "1.15.2",
    "name": "1.15.2",
    "release_target": "1.15.2",
    "type": "release",
    "stable": true,
    "data_version": 2230,
    "protocol_version": 578,
    "data_pack_version": 5,
    "data_pack_version_minor": 0,
    "resource_pack_version": 5,
    "resource_pack_version_minor": 0,
    "build_time": "2020-01-17T10:02:11+00:00",
    "release_time": "2020-01-17T10:03:52+00:00",
    "sha1": "e9d0adb8f642abe422909ede50f651b2b58a3573"
  },
  {
    "id": "1.15.1",
    "name": "1.15.1",
    "release_target": "1.15.1",
    "type": "release",
    "stable": true,
    "data_version": 2227,
    "protocol_version": 575,
    "data_pack_version": 5,
    "data_pack_version_minor": 0,
    "resource_pack_version": 5,
    "resource_pack_version_minor": 0,
    "build_time": "2019-12-16T10:28:09+00:00",
    "release_time": "2019-12-16T10:29:47+00:00",
    "sha1": "18c3063de87ae126b4e017121219ba802be0755b"
  },
  {
    "id": "1.15",
    "name": "1.15",
    "release_target": "1.15",
    "type": "release",
    "stable": true,
    "data_version": 2225,
    "protocol_version": 573,
    "data_pack_version": 5,
    "data_pack_version_minor": 0,
    "resource_pack_version": 5,
    "resource_pack_version_minor": 0,
    "build_time": "2019-12-09T13:11:56+00:00",
    "release_time": "2019-12-09T13:13:38+00:00",
    "sha1": "833322370ab320e77717097082effe1d124d48bd"
  },
  {
    "id": "1.14.4",
    "name": "1.14.4",
    "release_target": "1.14.4",
    "type": "release",
    "stable": true,
    "data_version": 1976,
    "protocol_version": 498,
    "data_pack_version": 4,
    "data_pack_version_minor": 0,
    "resource_pack_version": 4,
    "resource_pack_version_minor": 0,
    "build_time": "2019-07-19T09:24:08+00:00",
    "release_time": "2019-07-19T09:25:47+00:00",
    "sha1": "be146d5f66a3627ed0a87c234c4d8dde8ab35098"
  },
  {
    "id": "1.14.3",
    "name": "1.14.3",
    "release_target": "1.14.3",
    "type": "release",
    "stable": true,
    "data_version": 1968,
    "protocol_version": 490,
    "data_pack_version": 4,
    "data_pack_version_minor": 0,
    "resource_pack_version": 4,
    "resource_pack_version_minor": 0,
    "build_time": "2019-06-24T12:51:13+00:00",
    "release_time": "2019-06-24T12:52:52+00:00",
    "sha1": "e21618620e02be5a14543d1d17ffdba941d09aa8"
  },
  {
    "id": "1.14.2",
    "name": "1.14.2",
    "release_target": "1.14.2",
    "type": "release",
    "stable": true,
    "data_version": 1963,
    "protocol_version": 485,
    "data_pack_version": 4,
    "data_pack_version_minor": 0,
    "resource_pack_version": 4,
    "resource_pack_version_minor": 0,
    "build_time": "2019-05-27T11:46:41+00:00",
    "release_time": "2019-05-27T11:48:25+00:00",
    "sha1": "83299b3bf3139ebd9ae5547b3144dcf68d4cb1fd"
  },
  {
    "id": "1.14.1",
    "name": "1.14.1",
    "release_target": "1.14.1",
    "type": "release",
    "stable": false,
    "data_version": 1957,
    "protocol_version": 480,
    "data_pack_version": 4,
    "data_pack_version_minor": 0,
    "resource_pack_version": 4,
    "resource_pack_version_minor": 0,
    "build_time": "2019-05-13T11:08:37+00:00",
    "release_time": "2019-05-13T11:10:12+00:00",
    "sha1": "183e49ba0fabb5ef8a304f8f5907fa887f40c466"
  },
  {
    "id": "1.14",
    "name": "1.14",
    "release_target": "1.14",
    "type": "release",
    "stable": false,
    "data_version": 1952,
    "protocol_version": 477,
    "data_pack_version": 4,
    "data_pack_version_minor": 0,
    "resource_pack_version": 4,
    "resource_pack_version_minor": 0,
    "build_time": "2019-04-23T14:51:09+00:00",
    "release_time": "2019-04-23T14:52:44+00:00",
    "sha1": "0fd01dd81eaa451d3130b1cf025a10f129585b10"
  }
]